setup.py
funds_data_wyr/__init__.py
funds_data_wyr/funds_data.py
funds_data_wyr/funds_download.py
funds_data_wyr/funds_gen_sorting_files.py
funds_data_wyr/funds_get_top_ones.py
funds_data_wyr/settings.py
funds_data_wyr.egg-info/PKG-INFO
funds_data_wyr.egg-info/SOURCES.txt
funds_data_wyr.egg-info/dependency_links.txt
funds_data_wyr.egg-info/entry_points.txt
funds_data_wyr.egg-info/not-zip-safe
funds_data_wyr.egg-info/top_level.txt