Metadata-Version: 1.1
Name: funds-data-wyr
Version: 0.99
Summary: This package can download funds data from http://huobijijin.com and then analyze the data for giving valuable funds.
Home-page: https://github.com/FinixLei/FundsData
Author: Finix Lei
Author-email: finixlei@gmail.com
License: Apache License, Version 2.0
Platform: UNKNOWN
Classifier: Development Status :: 3 - Alpha
Classifier: Environment :: Web Environment
Classifier: Intended Audience :: Developers
Classifier: Operating System :: OS Independent
Classifier: Programming Language :: Python
